README.rst
setup.cfg
setup.py
django_humanstxt.egg-info/PKG-INFO
django_humanstxt.egg-info/SOURCES.txt
django_humanstxt.egg-info/dependency_links.txt
django_humanstxt.egg-info/requires.txt
django_humanstxt.egg-info/top_level.txt
humanstxt/__init__.py
humanstxt/admin.py
humanstxt/models.py
humanstxt/urls.py
humanstxt/views.py